py_classification_cache/__init__.py
py_classification_cache/pycc.py
py_classification_cache-0.0.2.dist-info/LICENSE
py_classification_cache-0.0.2.dist-info/METADATA
py_classification_cache-0.0.2.dist-info/WHEEL
py_classification_cache-0.0.2.dist-info/top_level.txt
py_classification_cache-0.0.2.dist-info/RECORD
