Metadata-Version: 2.1
Name: py-classification-cache
Version: 0.0.2
Summary: Python classification cache
Home-page: https://github.com/p208p2002/py-classification-cache
Author: Philip Huang
Author-email: p208p2002@gmail.com
License: UNKNOWN
Platform: UNKNOWN
Classifier: Programming Language :: Python :: 3
Classifier: License :: OSI Approved :: MIT License
Classifier: Operating System :: OS Independent
Requires-Dist: pypinyin (==0.35.4)
